[
    {
        "supplierName": "Depot Home"
    },
    {
        "supplierName": "Global Supplies"
    },
    {
        "supplierName": "Tech Parts Co."
    },
    {
        "supplierName": "Home Goods Inc."
    },
    {
        "supplierName": "Auto Parts Ltd."
    },
    {
        "supplierName": "Fresh Foods Co."
    },
    {
        "supplierName": "Textile Supplies"
    },
    {
        "supplierName": "Building Materials Co."
    },
    {
        "supplierName": "Cosmetics Corp."
    },
    {
        "supplierName": "Medical Supplies Inc."
    }
]
